AUTHORS.rst
CHANGELOG.rst
LICENSE
MANIFEST.in
README.rst
setup.py
panya_show.egg-info/PKG-INFO
panya_show.egg-info/SOURCES.txt
panya_show.egg-info/dependency_links.txt
panya_show.egg-info/not-zip-safe
panya_show.egg-info/requires.txt
panya_show.egg-info/top_level.txt
show/__init__.py
show/admin.py
show/forms.py
show/generator.py
show/models.py
show/tests.py
show/urls.py
show/view_modifiers.py
show/views.py
show/fixtures/photosizes.json
show/templates/show/radioshow_entryitem_list.html
show/templates/show/showcontributor_appearance_list.html
show/templates/show/showcontributor_contact.html
show/templates/show/showcontributor_content_detail.html
show/templates/show/showcontributor_content_list.html
show/templates/show/showcontributor_detail.html
show/templates/show/inclusion_tags/radioshow_entryitem_list_block.html
show/templates/show/inclusion_tags/radioshow_entryitem_listing.html
show/templates/show/inclusion_tags/showcontributor_detail.html
show/templates/show/inclusion_tags/showcontributor_header.html
show/templatetags/__init__.py
show/templatetags/show_inclusion_tags.py